onepassword_secrets_backend/__init__.py
onepassword_secrets_backend/one_password_backend.py
onepassword_secrets_backend-0.0.4.dist-info/LICENSE.txt
onepassword_secrets_backend-0.0.4.dist-info/METADATA
onepassword_secrets_backend-0.0.4.dist-info/WHEEL
onepassword_secrets_backend-0.0.4.dist-info/top_level.txt
onepassword_secrets_backend-0.0.4.dist-info/RECORD
