Metadata-Version: 2.1
Name: onepassword-secrets-backend
Version: 0.0.4
Summary: Custom 1password secrets backend for airflow
Classifier: Development Status :: 3 - Alpha
Classifier: Intended Audience :: Developers
Classifier: Topic :: Software Development :: Build Tools
Classifier: Programming Language :: Python :: 3
Classifier: License :: OSI Approved :: MIT License
Classifier: Operating System :: OS Independent
Requires-Python: >=3.8
License-File: LICENSE.txt
Requires-Dist: onepasswordconnectsdk ==1.3.0
Requires-Dist: apache-airflow >=2.5.1
